{ "frames": [
   {
    "filename": "chasing_lava 0.ase",
    "frame": { "x": 0, "y": 0, "w": 32, "h": 32 },
    "rotated": false,
    "trimmed": false,
    "spriteSourceSize": { "x": 0, "y": 0, "w": 32, "h": 32 },
    "sourceSize": { "w": 32, "h": 32 },
    "duration": 82
   },
   {
    "filename": "chasing_lava 1.ase",
    "frame": { "x": 0, "y": 0, "w": 32, "h": 32 },
    "rotated": false,
    "trimmed": false,
    "spriteSourceSize": { "x": 0, "y": 0, "w": 32, "h": 32 },
    "sourceSize": { "w": 32, "h": 32 },
    "duration": 82
   },
   {
    "filename": "chasing_lava 2.ase",
    "frame": { "x": 0, "y": 0, "w": 32, "h": 32 },
    "rotated": false,
    "trimmed": false,
    "spriteSourceSize": { "x": 0, "y": 0, "w": 32, "h": 32 },
    "sourceSize": { "w": 32, "h": 32 },
    "duration": 82
   },
   {
    "filename": "chasing_lava 3.ase",
    "frame": { "x": 0, "y": 0, "w": 32, "h": 32 },
    "rotated": false,
    "trimmed": false,
    "spriteSourceSize": { "x": 0, "y": 0, "w": 32, "h": 32 },
    "sourceSize": { "w": 32, "h": 32 },
    "duration": 82
   },
   {
    "filename": "chasing_lava 4.ase",
    "frame": { "x": 0, "y": 0, "w": 32, "h": 32 },
    "rotated": false,
    "trimmed": false,
    "spriteSourceSize": { "x": 0, "y": 0, "w": 32, "h": 32 },
    "sourceSize": { "w": 32, "h": 32 },
    "duration": 82
   },
   {
    "filename": "chasing_lava 5.ase",
    "frame": { "x": 32, "y": 0, "w": 32, "h": 32 },
    "rotated": false,
    "trimmed": false,
    "spriteSourceSize": { "x": 0, "y": 0, "w": 32, "h": 32 },
    "sourceSize": { "w": 32, "h": 32 },
    "duration": 82
   },
   {
    "filename": "chasing_lava 6.ase",
    "frame": { "x": 64, "y": 0, "w": 32, "h": 32 },
    "rotated": false,
    "trimmed": false,
    "spriteSourceSize": { "x": 0, "y": 0, "w": 32, "h": 32 },
    "sourceSize": { "w": 32, "h": 32 },
    "duration": 82
   },
   {
    "filename": "chasing_lava 7.ase",
    "frame": { "x": 96, "y": 0, "w": 32, "h": 32 },
    "rotated": false,
    "trimmed": false,
    "spriteSourceSize": { "x": 0, "y": 0, "w": 32, "h": 32 },
    "sourceSize": { "w": 32, "h": 32 },
    "duration": 82
   },
   {
    "filename": "chasing_lava 8.ase",
    "frame": { "x": 0, "y": 32, "w": 32, "h": 32 },
    "rotated": false,
    "trimmed": false,
    "spriteSourceSize": { "x": 0, "y": 0, "w": 32, "h": 32 },
    "sourceSize": { "w": 32, "h": 32 },
    "duration": 82
   },
   {
    "filename": "chasing_lava 9.ase",
    "frame": { "x": 32, "y": 32, "w": 32, "h": 32 },
    "rotated": false,
    "trimmed": false,
    "spriteSourceSize": { "x": 0, "y": 0, "w": 32, "h": 32 },
    "sourceSize": { "w": 32, "h": 32 },
    "duration": 82
   },
   {
    "filename": "chasing_lava 10.ase",
    "frame": { "x": 64, "y": 32, "w": 32, "h": 32 },
    "rotated": false,
    "trimmed": false,
    "spriteSourceSize": { "x": 0, "y": 0, "w": 32, "h": 32 },
    "sourceSize": { "w": 32, "h": 32 },
    "duration": 82
   },
   {
    "filename": "chasing_lava 11.ase",
    "frame": { "x": 96, "y": 32, "w": 32, "h": 32 },
    "rotated": false,
    "trimmed": false,
    "spriteSourceSize": { "x": 0, "y": 0, "w": 32, "h": 32 },
    "sourceSize": { "w": 32, "h": 32 },
    "duration": 82
   },
   {
    "filename": "chasing_lava 12.ase",
    "frame": { "x": 0, "y": 64, "w": 32, "h": 32 },
    "rotated": false,
    "trimmed": false,
    "spriteSourceSize": { "x": 0, "y": 0, "w": 32, "h": 32 },
    "sourceSize": { "w": 32, "h": 32 },
    "duration": 82
   },
   {
    "filename": "chasing_lava 13.ase",
    "frame": { "x": 32, "y": 64, "w": 32, "h": 32 },
    "rotated": false,
    "trimmed": false,
    "spriteSourceSize": { "x": 0, "y": 0, "w": 32, "h": 32 },
    "sourceSize": { "w": 32, "h": 32 },
    "duration": 82
   },
   {
    "filename": "chasing_lava 14.ase",
    "frame": { "x": 64, "y": 64, "w": 32, "h": 32 },
    "rotated": false,
    "trimmed": false,
    "spriteSourceSize": { "x": 0, "y": 0, "w": 32, "h": 32 },
    "sourceSize": { "w": 32, "h": 32 },
    "duration": 82
   },
   {
    "filename": "chasing_lava 15.ase",
    "frame": { "x": 96, "y": 64, "w": 32, "h": 32 },
    "rotated": false,
    "trimmed": false,
    "spriteSourceSize": { "x": 0, "y": 0, "w": 32, "h": 32 },
    "sourceSize": { "w": 32, "h": 32 },
    "duration": 82
   },
   {
    "filename": "chasing_lava 16.ase",
    "frame": { "x": 0, "y": 96, "w": 32, "h": 32 },
    "rotated": false,
    "trimmed": false,
    "spriteSourceSize": { "x": 0, "y": 0, "w": 32, "h": 32 },
    "sourceSize": { "w": 32, "h": 32 },
    "duration": 82
   },
   {
    "filename": "chasing_lava 17.ase",
    "frame": { "x": 32, "y": 96, "w": 32, "h": 32 },
    "rotated": false,
    "trimmed": false,
    "spriteSourceSize": { "x": 0, "y": 0, "w": 32, "h": 32 },
    "sourceSize": { "w": 32, "h": 32 },
    "duration": 82
   },
   {
    "filename": "chasing_lava 18.ase",
    "frame": { "x": 64, "y": 96, "w": 32, "h": 32 },
    "rotated": false,
    "trimmed": false,
    "spriteSourceSize": { "x": 0, "y": 0, "w": 32, "h": 32 },
    "sourceSize": { "w": 32, "h": 32 },
    "duration": 82
   },
   {
    "filename": "chasing_lava 19.ase",
    "frame": { "x": 96, "y": 96, "w": 32, "h": 32 },
    "rotated": false,
    "trimmed": false,
    "spriteSourceSize": { "x": 0, "y": 0, "w": 32, "h": 32 },
    "sourceSize": { "w": 32, "h": 32 },
    "duration": 82
   }
 ],
 "meta": {
  "app": "https://www.aseprite.org/",
  "version": "1.3-rc1-x64",
  "image": "lava.png",
  "format": "RGBA8888",
  "size": { "w": 128, "h": 128 },
  "scale": "1",
  "frameTags": [
   { "name": "plain", "from": 0, "to": 4, "direction": "forward", "color": "#000000ff" },
   { "name": "idle", "from": 5, "to": 9, "direction": "forward", "color": "#000000ff" },
   { "name": "near", "from": 10, "to": 14, "direction": "forward", "color": "#000000ff" },
   { "name": "fall", "from": 15, "to": 19, "direction": "forward", "color": "#000000ff" }
  ]
 }
}
